OpenWeatherMapLibrary/OpenWeatherMapLibrary.py
OpenWeatherMapLibrary/__init__.py
robotframework_openweathermap-1.0.4.dist-info/LICENSE
robotframework_openweathermap-1.0.4.dist-info/METADATA
robotframework_openweathermap-1.0.4.dist-info/WHEEL
robotframework_openweathermap-1.0.4.dist-info/top_level.txt
robotframework_openweathermap-1.0.4.dist-info/RECORD
